<?xml version="1.0" encoding="utf-8"?>
<publishData>
  <publishProfile publishUrl="ftp://jobs/" deleteExistingFiles="True" ftpAnonymousLogin="False" ftpPassiveMode="True" msdeploySite="" msdeploySiteID="" msdeployRemoteSitePhysicalPath="" msdeployAllowUntrustedCertificate="False" msdeploySkipExtraFilesOnServer="True" msdeployMarkAsApp="False" profileName="Profile1" publishMethod="FTP" replaceMatchingFiles="False" userName="admin" savePWD="True" userPWD="AQAAANCMnd8BFdERjHoAwE/Cl+sBAAAAW7QUe6dDO0u4GwolyFfjvQAAAAACAAAAAAADZgAAwAAAABAAAAAJi6z8MVs4eLVjsByly1x2AAAAAASAAACgAAAAEAAAANPynBKwQbV+U7cEd6wi6LkIAAAA7aseFktfnXwUAAAAgMEPwFkaoaMPK5djmvPXsETNBKU=" SelectedForPublish="True">
    <file relUrl="IMG/Used/arw_nav_prev.png" publishTime="08/12/2011 17:16:26" />
    <file relUrl="Default.aspx" publishTime="11/17/2011 12:44:40" />
    <file relUrl="MembershipPages/CreateNewUserPage.aspx" publishTime="03/04/2011 17:36:16" />
    <file relUrl="bin/Scripts/jquery.alerts.js" publishTime="08/12/2011 11:48:14" />
    <file relUrl="Scripts/jquery.alerts.js" publishTime="08/12/2011 11:48:14" />
    <file relUrl="Web.config" publishTime="11/17/2011 12:50:01" />
    <file relUrl="bin/Scripts/html5.js" publishTime="03/15/2011 11:35:06" />
    <file relUrl="IMG/Used/arw_nav_next.png" publishTime="08/12/2011 17:16:26" />
    <file relUrl="IMG/Used/ico_do_delete.png" publishTime="08/12/2011 12:18:11" />
    <file relUrl="MemberPage/MemberPage1.aspx" publishTime="09/02/2011 16:48:41" />
    <file relUrl="IMG/bgr_wide_yellow.png" publishTime="08/12/2011 11:23:40" />
    <file relUrl="bin/IMG/arrow1.jpg" publishTime="04/22/2011 16:35:55" />
    <file relUrl="bin/IMG/supprimer.png" publishTime="05/09/2011 18:11:30" />
    <file relUrl="Global.asax" publishTime="11/17/2011 13:03:46" />
    <file relUrl="bin/nunit.framework.dll" publishTime="12/14/2010 14:18:04" />
    <file relUrl="IMG/supprimer.png" publishTime="05/09/2011 18:11:30" />
    <file relUrl="bin/IMG/bgr_wide_yellow.png" publishTime="08/12/2011 11:23:40" />
    <file relUrl="IMG/Used/Note1.png" publishTime="08/12/2011 12:30:31" />
    <file relUrl="IMG/pilgrim_with_turkey.gif" publishTime="05/05/2011 17:09:39" />
    <file relUrl="MemberPage/AnnonceInf.aspx" publishTime="05/10/2011 15:53:25" />
    <file relUrl="Scripts/jquery-1.4.1.min.js" publishTime="02/23/2011 17:12:01" />
    <file relUrl="IMG/Used/ico_do_save.png" publishTime="08/12/2011 12:18:11" />
    <file relUrl="bin/IMG/bgr_header_Jobs.png" publishTime="03/22/2011 15:15:14" />
    <file relUrl="bin/WebApp7.dll" publishTime="11/17/2011 16:03:57" />
    <file relUrl="bin/Scripts/images/help.gif" publishTime="08/12/2011 11:48:12" />
    <file relUrl="Scripts/jquery-1.4.1.js" publishTime="02/23/2011 17:12:00" />
    <file relUrl="IMG/Rappeler.png" publishTime="05/09/2011 18:11:30" />
    <file relUrl="bin/Mono.Security.dll" publishTime="08/27/2005 00:59:12" />
    <file relUrl="Scripts/images/title.gif" publishTime="08/12/2011 11:48:12" />
    <file relUrl="bin/NUnitAsp.dll" publishTime="06/21/2007 00:56:28" />
    <file relUrl="bin/IMG/pilgrim_with_turkey.gif" publishTime="05/05/2011 17:09:39" />
    <file relUrl="bin/Scripts/images/title.gif" publishTime="08/12/2011 11:48:12" />
    <file relUrl="bin/IMG/Rappeler.png" publishTime="05/09/2011 18:11:30" />
    <file relUrl="Scripts/html5.js" publishTime="03/15/2011 11:35:06" />
    <file relUrl="Scripts/jquery-1.4.1-vsdoc.js" publishTime="02/23/2011 17:12:00" />
    <file relUrl="Scripts/images/help.gif" publishTime="08/12/2011 11:48:12" />
    <file relUrl="Scripts/jquery.alerts.css" publishTime="08/12/2011 11:47:23" />
    <file relUrl="IMG/Used/arw_dir_black_right.png" publishTime="08/16/2011 15:25:23" />
    <file relUrl="IMG/Conserver.png" publishTime="05/09/2011 18:04:06" />
    <file relUrl="IMG/Used/arw_nav_top.png" publishTime="08/12/2011 17:16:26" />
    <file relUrl="MemberPage/MemberPages.Master" publishTime="08/23/2011 11:59:03" />
    <file relUrl="MemberPage/Profile.aspx" publishTime="02/28/2011 12:35:28" />
    <file relUrl="MemberPage/MesRappels.aspx" publishTime="09/02/2011 16:54:42" />
    <file relUrl="bin/Scripts/jquery-1.4.1-vsdoc.js" publishTime="02/23/2011 17:12:00" />
    <file relUrl="IMG/bgr_login_Jobs.png" publishTime="03/22/2011 15:15:18" />
    <file relUrl="bin/Scripts/images/important.gif" publishTime="08/12/2011 11:48:12" />
    <file relUrl="MembershipPages/PasswordRecoveryPage.aspx" publishTime="03/15/2011 10:49:27" />
    <file relUrl="bin/nunit.framework.xml" publishTime="12/14/2010 14:18:04" />
    <file relUrl="bin/Npgsql.dll" publishTime="08/27/2005 00:59:12" />
    <file relUrl="Scripts/images/info.gif" publishTime="08/12/2011 11:48:12" />
    <file relUrl="MemberPage/MesRecherches.aspx" publishTime="04/22/2011 15:47:51" />
    <file relUrl="bin/Scripts/jquery-1.4.1.js" publishTime="02/23/2011 17:12:00" />
    <file relUrl="bin/IMG/bgr_login_Jobs.png" publishTime="03/22/2011 15:15:18" />
    <file relUrl="bin/WebApp7.pdb" publishTime="11/17/2011 16:03:57" />
    <file relUrl="MemberPage/ChangePasswordPage.aspx" publishTime="02/28/2011 16:31:47" />
    <file relUrl="IMG/bgr_header_Jobs.png" publishTime="03/22/2011 15:15:14" />
    <file relUrl="bin/IMG/Conserver.png" publishTime="05/09/2011 18:04:06" />
    <file relUrl="bin/Scripts/jquery-1.4.1.min.js" publishTime="02/23/2011 17:12:01" />
    <file relUrl="bin/Scripts/images/info.gif" publishTime="08/12/2011 11:48:12" />
    <file relUrl="MemberPage/AnnoncePage.aspx" publishTime="06/28/2011 16:58:36" />
    <file relUrl="IMG/Used/arw_nav_bot.png" publishTime="08/12/2011 17:16:26" />
    <file relUrl="bin/AjaxControlToolkit.dll" publishTime="05/12/2010 12:10:28" />
    <file relUrl="bin/Scripts/jquery.alerts.css" publishTime="08/12/2011 11:47:23" />
    <file relUrl="MemberPage/RechercherPage.aspx" publishTime="05/30/2011 16:05:32" />
    <file relUrl="IMG/arrow1.jpg" publishTime="04/22/2011 16:35:55" />
    <file relUrl="Scripts/images/important.gif" publishTime="08/12/2011 11:48:12" />
    <file relUrl="IMG/Used/sts_ar.png" publishTime="08/12/2011 12:22:18" />
  </publishProfile>
</publishData>